lmkit/__init__.py
lmkit/version.py
lmkit-0.0.1.dist-info/METADATA
lmkit-0.0.1.dist-info/WHEEL
lmkit-0.0.1.dist-info/top_level.txt
lmkit-0.0.1.dist-info/RECORD
