Metadata-Version: 2.1
Name: lmkit
Version: 0.0.1
Summary: Universal library for working with LLMs
Home-page: https://www.braintrustdata.com
Author: BrainTrust
Author-email: info@braintrustdata.com
Classifier: Programming Language :: Python :: 3
Classifier: Operating System :: OS Independent
Requires-Python: >=3.7.0
Requires-Dist: openai
Requires-Dist: GitPython
Requires-Dist: requests
Provides-Extra: all
Requires-Dist: IPython ; extra == 'all'
Requires-Dist: black ; extra == 'all'
Requires-Dist: build ; extra == 'all'
Requires-Dist: flake8 ; extra == 'all'
Requires-Dist: flake8-isort ; extra == 'all'
Requires-Dist: isort (==5.10.1) ; extra == 'all'
Requires-Dist: pre-commit ; extra == 'all'
Requires-Dist: pydoc-markdown[novella] ; extra == 'all'
Requires-Dist: pytest ; extra == 'all'
Requires-Dist: twine ; extra == 'all'
Provides-Extra: dev
Requires-Dist: black ; extra == 'dev'
Requires-Dist: build ; extra == 'dev'
Requires-Dist: flake8 ; extra == 'dev'
Requires-Dist: flake8-isort ; extra == 'dev'
Requires-Dist: IPython ; extra == 'dev'
Requires-Dist: isort (==5.10.1) ; extra == 'dev'
Requires-Dist: pre-commit ; extra == 'dev'
Requires-Dist: pytest ; extra == 'dev'
Requires-Dist: twine ; extra == 'dev'
Provides-Extra: doc
Requires-Dist: pydoc-markdown[novella] ; extra == 'doc'
